README.rst
setup.cfg
setup.py
examples/__init__.py
examples/custom_server.py
examples/mrpc121.py
examples/pip_sql_rpc.py
fispip/__init__.py
fispip/__main__.py
fispip/mtm.py
fispip/mysix.py
fispip/pip.py
fispip.egg-info/PKG-INFO
fispip.egg-info/SOURCES.txt
fispip.egg-info/dependency_links.txt
fispip.egg-info/top_level.txt