Metadata-Version: 1.1
Name: fispip
Version: 0.0.3
Summary: Python FIS MTM/PIP SQL/RPC Interface
Home-page: https://github.com/fopina/pyfispip
Author: Filipe Pina
Author-email: fopina@skmobi.com
License: MIT
Download-URL: https://github.com/fopina/pyfispip/tarball/v0.0.3
Keywords: database,gtm,mtm,pip,fis
Platform: UNKNOWN
Classifier: Development Status :: 4 - Beta
Classifier: Intended Audience :: Developers
Classifier: License :: OSI Approved :: MIT License
Classifier: Operating System :: OS Independent
Classifier: Programming Language :: Python
Classifier: Programming Language :: Python
Classifier: Programming Language :: Python :: 2
Classifier: Programming Language :: Python :: 2.7
Classifier: Programming Language :: Python :: 3
Classifier: Programming Language :: Python :: 3.0
Classifier: Programming Language :: Python :: 3.1
Classifier: Programming Language :: Python :: 3.2
Classifier: Programming Language :: Python :: 3.3
Classifier: Programming Language :: Python :: 3.4
Classifier: Programming Language :: Python :: 3.5
